assess_mozilla_aws_security_infrastructure/__init__.py
assess_mozilla_aws_security_infrastructure/persistent_cache.py
assess_mozilla_aws_security_infrastructure-1.0.dist-info/LICENSE
assess_mozilla_aws_security_infrastructure-1.0.dist-info/METADATA
assess_mozilla_aws_security_infrastructure-1.0.dist-info/WHEEL
assess_mozilla_aws_security_infrastructure-1.0.dist-info/entry_points.txt
assess_mozilla_aws_security_infrastructure-1.0.dist-info/top_level.txt
assess_mozilla_aws_security_infrastructure-1.0.dist-info/RECORD
