Metadata-Version: 2.1
Name: assess-mozilla-aws-security-infrastructure
Version: 1.0
Summary: Tool to assess the state of security infrastructure in Mozilla's AWS accounts
Home-page: https://github.com/mozilla/assess-mozilla-aws-security-infrastructure
Author: Gene Wood
Author-email: gene@mozilla.com
License: MPL-2.0
License-File: LICENSE
Requires-Dist: boto3
Requires-Dist: xdg
